functions_by_nakiteniz/README.md
functions_by_nakiteniz/math_functions.py
functions_by_nakiteniz-0.1.0.dist-info/WHEEL
functions_by_nakiteniz-0.1.0.dist-info/METADATA
functions_by_nakiteniz-0.1.0.dist-info/RECORD
