Metadata-Version: 2.1
Name: functions-by-nakiteniz
Version: 0.1.0
Summary: This is our test project
Author: somename
Author-email: nargizafernandez@gmail.com
Requires-Python: >=3.10,<4.0
Classifier: Programming Language :: Python :: 3
Classifier: Programming Language :: Python :: 3.10
Classifier: Programming Language :: Python :: 3.11
